koilerplate/__init__.py
koilerplate/folders.py
koilerplate/offline.py
koilerplate/pushover.py
koilerplate/zipout.py
koilerplate-0.1.3.dist-info/LICENSE.txt
koilerplate-0.1.3.dist-info/METADATA
koilerplate-0.1.3.dist-info/WHEEL
koilerplate-0.1.3.dist-info/top_level.txt
koilerplate-0.1.3.dist-info/RECORD
