Metadata-Version: 2.1
Name: koilerplate
Version: 0.1.3
Summary: Helper boilerplate code that is useful in Kaggle competitions.
Home-page: https://github.com/AScholan/koilerplate.git
Author: Andrew Scholan
Author-email: andrew.scholan@scholan.com
License: MIT
Project-URL: Bug Tracker, https://github.com/AScholan/koilerplate/issues
Keywords: kaggle
Platform: UNKNOWN
Classifier: Development Status :: 3 - Alpha
Classifier: Framework :: Jupyter
Classifier: Topic :: Scientific/Engineering :: Artificial Intelligence
Classifier: Topic :: Utilities
Classifier: Programming Language :: Python :: 3
Classifier: License :: OSI Approved :: MIT License
Classifier: Operating System :: OS Independent
Classifier: Intended Audience :: Developers
Classifier: Intended Audience :: Science/Research
Classifier: Natural Language :: English
Classifier: Typing :: Typed
Requires-Python: >=3.7
License-File: LICENSE.txt
Requires-Dist: requests
